naludaq/__init__.py
naludaq/_version.py
naludaq/naludaq.py
naludaq/backend/__init__.py
naludaq/backend/client.py
naludaq/backend/context.py
naludaq/backend/exceptions.py
naludaq/backend/managers/__init__.py
naludaq/backend/managers/acquisitions.py
naludaq/backend/managers/base.py
naludaq/backend/managers/config.py
naludaq/backend/managers/connection.py
naludaq/backend/managers/io.py
naludaq/backend/models/__init__.py
naludaq/backend/models/acquisition.py
naludaq/backend/models/device.py
naludaq/board/__init__.py
naludaq/board/board_inits.py
naludaq/board/params.py
naludaq/board/connections/_FTDI.py
naludaq/board/connections/_MockUART.py
naludaq/board/connections/_UART.py
naludaq/board/connections/_USB.py
naludaq/board/connections/__init__.py
naludaq/board/connections/base_connection.py
naludaq/board/connections/base_ethernet.py
naludaq/board/connections/base_serial.py
naludaq/board/connections/connection_factory.py
naludaq/board/connections/tcp.py
naludaq/board/connections/udp.py
naludaq/board/initializers/__init__.py
naludaq/board/initializers/aardvarcv3.py
naludaq/board/initializers/aodsoc.py
naludaq/board/initializers/asocv3s.py
naludaq/board/initializers/hiper.py
naludaq/board/initializers/init_aodsv2_eval.py
naludaq/board/initializers/init_hdsocv1.py
naludaq/board/initializers/init_hdsocv2.py
naludaq/board/initializers/init_udc.py
naludaq/board/initializers/init_upac96.py
naludaq/board/initializers/trbhm.py
naludaq/communication/__init__.py
naludaq/communication/_chip.py
naludaq/communication/_common.py
naludaq/communication/_fpga.py
naludaq/communication/analog_registers.py
naludaq/communication/chip_selection.py
naludaq/communication/control_registers.py
naludaq/communication/digital_registers.py
naludaq/communication/i2c.py
naludaq/communication/i2c_registers.py
naludaq/communication/registers.py
naludaq/communication/spi.py
naludaq/controllers/__init__.py
naludaq/controllers/controller.py
naludaq/controllers/project_controller.py
naludaq-0.34.3.dist-info/licenses/LICENSE.txt
naludaq-0.34.3.dist-info/METADATA
naludaq-0.34.3.dist-info/WHEEL
naludaq-0.34.3.dist-info/top_level.txt
naludaq-0.34.3.dist-info/RECORD
