Metadata-Version: 2.4
Name: naludaq
Version: 0.34.3
Summary: Backend package for Nalu Scientific hardware
Home-page: 
Author: Thomas Yang, Emily Lum, Terry Pham
Author-email: Marcus Luck <marcus@naluscientific.com>, Mitchell Matsumori-Kelly <mitchell@naluscientific.com>, Alvin Yang <alvin@naluscientific.com>, Kenneth Lauritzen <kenneth@naluscientific.com>, Ben Rotter <ben@naluscientific.com>
Classifier: Development Status :: 4 - Beta
Classifier: Environment :: Console
Classifier: Programming Language :: Python :: 3
Classifier: Intended Audience :: End Users/Desktop
Classifier: Intended Audience :: Developers
Classifier: License :: OSI Approved :: GNU General Public License v3 (GPLv3)
Classifier: Operating System :: OS Independent
Requires-Python: >=3.9
License-File: LICENSE.txt
Requires-Dist: naluconfigs>=17.3.0
Requires-Dist: ftd3xx>=1.0
Requires-Dist: naludaq_rs>=0.2.8
Requires-Dist: naluacq>=0.4.9
Requires-Dist: bayesian_optimization==1.4.3
Requires-Dist: deprecation
Requires-Dist: ftd2xx>=1.1.2
Requires-Dist: h5py
Requires-Dist: numpy<1.24
Requires-Dist: pyserial==3.4
Requires-Dist: pyyaml>=5.1.1
Requires-Dist: scikit-learn==1.1.3
Requires-Dist: requests
Provides-Extra: dev
Requires-Dist: pytest; extra == "dev"
Requires-Dist: pytest-mock; extra == "dev"
Requires-Dist: pytest-xdist; extra == "dev"
Requires-Dist: pytest-sugar; extra == "dev"
Dynamic: license-file
Dynamic: requires-python
